{
  "30468": {
    "name": "Dhurandhar: The Revenge",
    "dates": {
      "2026-03-21": {
        "summary": {
          "shows": 8,
          "sold": 1272,
          "seats": 1896,
          "occupancy": 67.09,
          "gross": 23136.0
        },
        "shows": [
          {
            "cinema": "CineStar Augsburg",
            "session": "120427",
            "time": "2026-03-21 20:10 CET",
            "sold": 62,
            "seats": 162,
            "gross": 1116.0
          },
          {
            "cinema": "CineStar Berlin - CUBIX am Alexanderplatz",
            "session": "155804",
            "time": "2026-03-21 19:00 CET",
            "sold": 0,
            "seats": 0,
            "gross": 0
          },
          {
            "cinema": "CineStar D\u00fcsseldorf",
            "session": "187945",
            "time": "2026-03-21 20:00 CET",
            "sold": 275,
            "seats": 596,
            "gross": 4950.0
          },
          {
            "cinema": "CineStar Erlangen",
            "session": "219824",
            "time": "2026-03-21 19:15 CET",
            "sold": 105,
            "seats": 148,
            "gross": 1890.0
          },
          {
            "cinema": "CineStar Erlangen",
            "session": "219834",
            "time": "2026-03-21 19:40 CET",
            "sold": 84,
            "seats": 119,
            "gross": 1512.0
          },
          {
            "cinema": "CineStar Frankfurt am Main Metropolis",
            "session": "274721",
            "time": "2026-03-21 19:30 CET",
            "sold": 491,
            "seats": 502,
            "gross": 9078.0
          },
          {
            "cinema": "CineStar Frankfurt am Main Metropolis",
            "session": "275597",
            "time": "2026-03-21 20:45 CET",
            "sold": 148,
            "seats": 152,
            "gross": 2664.0
          },
          {
            "cinema": "CineStar Saarbr\u00fccken",
            "session": "233214",
            "time": "2026-03-21 20:15 CET",
            "sold": 107,
            "seats": 217,
            "gross": 1926.0
          }
        ]
      },
      "2026-03-22": {
        "summary": {
          "shows": 18,
          "sold": 1585,
          "seats": 3654,
          "occupancy": 43.38,
          "gross": 28785.0
        },
        "shows": [
          {
            "cinema": "CineStar Augsburg",
            "session": "119035",
            "time": "2026-03-22 19:00 CET",
            "sold": 97,
            "seats": 149,
            "gross": 1746.0
          },
          {
            "cinema": "CineStar Augsburg",
            "session": "120426",
            "time": "2026-03-22 18:40 CET",
            "sold": 33,
            "seats": 162,
            "gross": 594.0
          },
          {
            "cinema": "CineStar Augsburg",
            "session": "246949",
            "time": "2026-03-22 19:10 CET",
            "sold": 0,
            "seats": 0,
            "gross": 0
          },
          {
            "cinema": "CineStar Augsburg",
            "session": "247410",
            "time": "2026-03-22 18:50 CET",
            "sold": 0,
            "seats": 0,
            "gross": 0
          },
          {
            "cinema": "CineStar Augsburg",
            "session": "247682",
            "time": "2026-03-22 15:00 CET",
            "sold": 0,
            "seats": 0,
            "gross": 0
          },
          {
            "cinema": "CineStar Augsburg",
            "session": "247764",
            "time": "2026-03-22 20:00 CET",
            "sold": 0,
            "seats": 0,
            "gross": 0
          },
          {
            "cinema": "CineStar Augsburg",
            "session": "247765",
            "time": "2026-03-22 14:00 CET",
            "sold": 0,
            "seats": 0,
            "gross": 0
          },
          {
            "cinema": "CineStar Berlin - CUBIX am Alexanderplatz",
            "session": "155356",
            "time": "2026-03-22 19:00 CET",
            "sold": 0,
            "seats": 0,
            "gross": 0
          },
          {
            "cinema": "CineStar Kristall-Palast - Bremen",
            "session": "32864",
            "time": "2026-03-22 19:00 CET",
            "sold": 13,
            "seats": 288,
            "gross": 234.0
          },
          {
            "cinema": "CineStar Chemnitz - Am Roten Turm",
            "session": "364124",
            "time": "2026-03-22 19:00 CET",
            "sold": 184,
            "seats": 407,
            "gross": 3312.0
          },
          {
            "cinema": "CineStar D\u00fcsseldorf",
            "session": "186744",
            "time": "2026-03-22 19:00 CET",
            "sold": 241,
            "seats": 596,
            "gross": 4338.0
          },
          {
            "cinema": "CineStar Erfurt",
            "session": "144891",
            "time": "2026-03-22 19:30 CET",
            "sold": 0,
            "seats": 0,
            "gross": 0
          },
          {
            "cinema": "CineStar Erlangen",
            "session": "218739",
            "time": "2026-03-22 19:00 CET",
            "sold": 354,
            "seats": 466,
            "gross": 6372.0
          },
          {
            "cinema": "CineStar Erlangen",
            "session": "219835",
            "time": "2026-03-22 19:20 CET",
            "sold": 25,
            "seats": 148,
            "gross": 450.0
          },
          {
            "cinema": "CineStar Frankfurt am Main Metropolis",
            "session": "274142",
            "time": "2026-03-22 19:30 CET",
            "sold": 379,
            "seats": 502,
            "gross": 7062.0
          },
          {
            "cinema": "CineStar Frankfurt am Main Metropolis",
            "session": "276000",
            "time": "2026-03-22 20:45 CET",
            "sold": 25,
            "seats": 285,
            "gross": 465.0
          },
          {
            "cinema": "CineStar Mainz",
            "session": "238927",
            "time": "2026-03-22 19:40 CET",
            "sold": 149,
            "seats": 298,
            "gross": 2682.0
          },
          {
            "cinema": "CineStar Siegen",
            "session": "186818",
            "time": "2026-03-22 19:30 CET",
            "sold": 85,
            "seats": 353,
            "gross": 1530.0
          }
        ]
      },
      "2026-03-23": {
        "summary": {
          "shows": 2,
          "sold": 258,
          "seats": 708,
          "occupancy": 36.44,
          "gross": 4848.0
        },
        "shows": [
          {
            "cinema": "CineStar Erlangen",
            "session": "219821",
            "time": "2026-03-23 19:00 CET",
            "sold": 25,
            "seats": 206,
            "gross": 450.0
          },
          {
            "cinema": "CineStar Frankfurt am Main Metropolis",
            "session": "275151",
            "time": "2026-03-23 19:30 CET",
            "sold": 233,
            "seats": 502,
            "gross": 4398.0
          }
        ]
      },
      "2026-03-24": {
        "summary": {
          "shows": 2,
          "sold": 140,
          "seats": 504,
          "occupancy": 27.78,
          "gross": 2613.0
        },
        "shows": [
          {
            "cinema": "CineStar Erlangen",
            "session": "219822",
            "time": "2026-03-24 19:00 CET",
            "sold": 40,
            "seats": 206,
            "gross": 720.0
          },
          {
            "cinema": "CineStar Frankfurt am Main Metropolis",
            "session": "275153",
            "time": "2026-03-24 19:30 CET",
            "sold": 100,
            "seats": 298,
            "gross": 1893.0
          }
        ]
      },
      "2026-03-25": {
        "summary": {
          "shows": 2,
          "sold": 82,
          "seats": 708,
          "occupancy": 11.58,
          "gross": 1581.0
        },
        "shows": [
          {
            "cinema": "CineStar Erlangen",
            "session": "219823",
            "time": "2026-03-25 19:00 CET",
            "sold": 10,
            "seats": 206,
            "gross": 180.0
          },
          {
            "cinema": "CineStar Frankfurt am Main Metropolis",
            "session": "275154",
            "time": "2026-03-25 19:15 CET",
            "sold": 72,
            "seats": 502,
            "gross": 1401.0
          }
        ]
      },
      "2026-03-26": {
        "summary": {
          "shows": 0,
          "sold": 0,
          "seats": 0,
          "occupancy": 0,
          "gross": 0
        },
        "shows": []
      },
      "2026-03-27": {
        "summary": {
          "shows": 1,
          "sold": 121,
          "seats": 502,
          "occupancy": 24.1,
          "gross": 2307.0
        },
        "shows": [
          {
            "cinema": "CineStar Frankfurt am Main Metropolis",
            "session": "275709",
            "time": "2026-03-27 19:30 CET",
            "sold": 121,
            "seats": 502,
            "gross": 2307.0
          }
        ]
      }
    }
  }
}