{
  "HO00001327": {
    "name": "dhurandhar: The Revenge",
    "dates": {
      "2026-03-24": {
        "summary": {
          "shows": 7,
          "sold": 568,
          "seats": 1096,
          "occupancy": 51.82,
          "gross": 7801.32
        },
        "shows": [
          {
            "cinema": "Berlin",
            "session": "53593",
            "time": "2026-03-24T20:10:00",
            "sold": 116,
            "seats": 120,
            "gross": 1545.8400000000008
          },
          {
            "cinema": "M\u00fcnchen",
            "session": "15776",
            "time": "2026-03-24T18:20:00",
            "sold": 87,
            "seats": 92,
            "gross": 1222.1300000000006
          },
          {
            "cinema": "Berlin",
            "session": "53438",
            "time": "2026-03-24T21:30:00",
            "sold": 110,
            "seats": 114,
            "gross": 1468.9000000000008
          },
          {
            "cinema": "Regensburg",
            "session": "15867",
            "time": "2026-03-24T19:00:00",
            "sold": 112,
            "seats": 174,
            "gross": 1553.8800000000008
          },
          {
            "cinema": "Magdeburg",
            "session": "33722",
            "time": "2026-03-24T17:50:00",
            "sold": 54,
            "seats": 81,
            "gross": 762.4600000000004
          },
          {
            "cinema": "Freiburg",
            "session": "18801",
            "time": "2026-03-24T19:30:00",
            "sold": 58,
            "seats": 62,
            "gross": 795.4200000000004
          },
          {
            "cinema": "Essen",
            "session": "40170",
            "time": "2026-03-24T20:15:00",
            "sold": 31,
            "seats": 453,
            "gross": 452.69000000000017
          }
        ]
      },
      "2026-03-25": {
        "summary": {
          "shows": 5,
          "sold": 192,
          "seats": 473,
          "occupancy": 40.59,
          "gross": 2709.08
        },
        "shows": [
          {
            "cinema": "Berlin",
            "session": "54490",
            "time": "2026-03-25T20:15:00",
            "sold": 20,
            "seats": 102,
            "gross": 287.80000000000007
          },
          {
            "cinema": "Berlin",
            "session": "53513",
            "time": "2026-03-25T19:00:00",
            "sold": 19,
            "seats": 21,
            "gross": 265.81000000000006
          },
          {
            "cinema": "Berlin",
            "session": "53536",
            "time": "2026-03-25T21:00:00",
            "sold": 62,
            "seats": 67,
            "gross": 860.3800000000005
          },
          {
            "cinema": "Essen",
            "session": "40140",
            "time": "2026-03-25T20:30:00",
            "sold": 9,
            "seats": 191,
            "gross": 134.91
          },
          {
            "cinema": "M\u00fcnchen",
            "session": "15714",
            "time": "2026-03-25T18:30:00",
            "sold": 82,
            "seats": 92,
            "gross": 1160.1800000000005
          }
        ]
      },
      "2026-03-30": {
        "summary": {
          "shows": 4,
          "sold": 56,
          "seats": 545,
          "occupancy": 10.28,
          "gross": 833.44
        },
        "shows": [
          {
            "cinema": "Essen",
            "session": "41045",
            "time": "2026-03-30T19:30:00",
            "sold": 46,
            "seats": 191,
            "gross": 689.5400000000003
          },
          {
            "cinema": "Berlin",
            "session": "54749",
            "time": "2026-03-30T20:50:00",
            "sold": 8,
            "seats": 102,
            "gross": 113.91999999999999
          },
          {
            "cinema": "Offenbach",
            "session": "17032",
            "time": "2026-03-30T19:00:00",
            "sold": 2,
            "seats": 171,
            "gross": 29.98
          },
          {
            "cinema": "Magdeburg",
            "session": "34281",
            "time": "2026-03-30T18:05:00",
            "sold": 0,
            "seats": 81,
            "gross": 0
          }
        ]
      },
      "2026-03-26": {
        "summary": {
          "shows": 5,
          "sold": 90,
          "seats": 655,
          "occupancy": 13.74,
          "gross": 1370.1
        },
        "shows": [
          {
            "cinema": "Berlin",
            "session": "54711",
            "time": "2026-03-26T20:30:00",
            "sold": 21,
            "seats": 120,
            "gross": 320.7900000000001
          },
          {
            "cinema": "M\u00fcnchen",
            "session": "15933",
            "time": "2026-03-26T18:30:00",
            "sold": 6,
            "seats": 92,
            "gross": 107.93999999999998
          },
          {
            "cinema": "Offenbach",
            "session": "17094",
            "time": "2026-03-26T18:50:00",
            "sold": 5,
            "seats": 171,
            "gross": 71.95
          },
          {
            "cinema": "Magdeburg",
            "session": "34279",
            "time": "2026-03-26T18:15:00",
            "sold": 8,
            "seats": 81,
            "gross": 119.91999999999999
          },
          {
            "cinema": "Essen",
            "session": "41032",
            "time": "2026-03-26T20:45:00",
            "sold": 50,
            "seats": 191,
            "gross": 749.5000000000003
          }
        ]
      },
      "2026-03-27": {
        "summary": {
          "shows": 22,
          "sold": 271,
          "seats": 3035,
          "occupancy": 8.93,
          "gross": 4004.29
        },
        "shows": [
          {
            "cinema": "Hannover",
            "session": "26320",
            "time": "2026-03-27T21:40:00",
            "sold": 0,
            "seats": 79,
            "gross": 0
          },
          {
            "cinema": "Berlin",
            "session": "54019",
            "time": "2026-03-27T20:20:00",
            "sold": 110,
            "seats": 114,
            "gross": 1573.9000000000008
          },
          {
            "cinema": "Berlin",
            "session": "54985",
            "time": "2026-03-27T12:35:00",
            "sold": 9,
            "seats": 102,
            "gross": 140.90999999999997
          },
          {
            "cinema": "Magdeburg",
            "session": "34255",
            "time": "2026-03-27T20:30:00",
            "sold": 4,
            "seats": 76,
            "gross": 59.96
          },
          {
            "cinema": "Sindelfingen",
            "session": "18693",
            "time": "2026-03-27T20:00:00",
            "sold": 7,
            "seats": 64,
            "gross": 104.92999999999999
          },
          {
            "cinema": "Hannover",
            "session": "26290",
            "time": "2026-03-27T20:20:00",
            "sold": 0,
            "seats": 226,
            "gross": 0
          },
          {
            "cinema": "Offenbach",
            "session": "17038",
            "time": "2026-03-27T20:30:00",
            "sold": 0,
            "seats": 171,
            "gross": 0
          },
          {
            "cinema": "Wolfsburg",
            "session": "14990",
            "time": "2026-03-27T20:20:00",
            "sold": 4,
            "seats": 163,
            "gross": 59.96
          },
          {
            "cinema": "W\u00fcrzburg",
            "session": "15518",
            "time": "2026-03-27T20:15:00",
            "sold": 5,
            "seats": 194,
            "gross": 74.95
          },
          {
            "cinema": "Stuttgart Liederhalle",
            "session": "18266",
            "time": "2026-03-27T20:30:00",
            "sold": 18,
            "seats": 100,
            "gross": 263.82000000000005
          },
          {
            "cinema": "Augsburg",
            "session": "26342",
            "time": "2026-03-27T20:10:00",
            "sold": 2,
            "seats": 299,
            "gross": 31.98
          },
          {
            "cinema": "G\u00f6ttingen",
            "session": "21476",
            "time": "2026-03-27T19:15:00",
            "sold": 1,
            "seats": 72,
            "gross": 14.99
          },
          {
            "cinema": "Halle",
            "session": "18561",
            "time": "2026-03-27T19:10:00",
            "sold": 4,
            "seats": 136,
            "gross": 59.96
          },
          {
            "cinema": "Freiburg",
            "session": "19511",
            "time": "2026-03-27T19:00:00",
            "sold": 4,
            "seats": 60,
            "gross": 71.96
          },
          {
            "cinema": "Bremen",
            "session": "21445",
            "time": "2026-03-27T20:15:00",
            "sold": 2,
            "seats": 178,
            "gross": 29.98
          },
          {
            "cinema": "Wuppertal",
            "session": "21390",
            "time": "2026-03-27T20:30:00",
            "sold": 0,
            "seats": 140,
            "gross": 0
          },
          {
            "cinema": "Kiel",
            "session": "48243",
            "time": "2026-03-27T20:15:00",
            "sold": 0,
            "seats": 94,
            "gross": 0
          },
          {
            "cinema": "Regensburg",
            "session": "16218",
            "time": "2026-03-27T20:20:00",
            "sold": 4,
            "seats": 124,
            "gross": 59.96
          },
          {
            "cinema": "Essen",
            "session": "41056",
            "time": "2026-03-27T21:15:00",
            "sold": 48,
            "seats": 191,
            "gross": 719.5200000000003
          },
          {
            "cinema": "Bielefeld",
            "session": "23836",
            "time": "2026-03-27T21:00:00",
            "sold": 0,
            "seats": 67,
            "gross": 0
          },
          {
            "cinema": "Essen",
            "session": "41057",
            "time": "2026-03-27T16:30:00",
            "sold": 49,
            "seats": 191,
            "gross": 737.5100000000003
          },
          {
            "cinema": "Dresden",
            "session": "18094",
            "time": "2026-03-27T19:00:00",
            "sold": 0,
            "seats": 194,
            "gross": 0
          }
        ]
      },
      "2026-03-29": {
        "summary": {
          "shows": 8,
          "sold": 97,
          "seats": 836,
          "occupancy": 11.6,
          "gross": 1480.03
        },
        "shows": [
          {
            "cinema": "Hannover",
            "session": "26306",
            "time": "2026-03-29T14:20:00",
            "sold": 10,
            "seats": 79,
            "gross": 149.9
          },
          {
            "cinema": "Berlin",
            "session": "54885",
            "time": "2026-03-29T20:20:00",
            "sold": 36,
            "seats": 120,
            "gross": 549.6400000000002
          },
          {
            "cinema": "Bielefeld",
            "session": "23811",
            "time": "2026-03-29T19:30:00",
            "sold": 0,
            "seats": 67,
            "gross": 0
          },
          {
            "cinema": "Sindelfingen",
            "session": "18628",
            "time": "2026-03-29T12:00:00",
            "sold": 31,
            "seats": 55,
            "gross": 468.69000000000017
          },
          {
            "cinema": "Regensburg",
            "session": "16257",
            "time": "2026-03-29T19:15:00",
            "sold": 0,
            "seats": 131,
            "gross": 0
          },
          {
            "cinema": "M\u00fcnchen",
            "session": "16034",
            "time": "2026-03-29T18:30:00",
            "sold": 0,
            "seats": 60,
            "gross": 0
          },
          {
            "cinema": "Stuttgart Liederhalle",
            "session": "18275",
            "time": "2026-03-29T19:00:00",
            "sold": 20,
            "seats": 100,
            "gross": 311.80000000000007
          },
          {
            "cinema": "Essen",
            "session": "41015",
            "time": "2026-03-29T20:00:00",
            "sold": 0,
            "seats": 224,
            "gross": 0
          }
        ]
      },
      "2026-03-28": {
        "summary": {
          "shows": 24,
          "sold": 404,
          "seats": 3319,
          "occupancy": 12.17,
          "gross": 5947.96
        },
        "shows": [
          {
            "cinema": "Freiburg",
            "session": "19515",
            "time": "2026-03-28T21:45:00",
            "sold": 0,
            "seats": 60,
            "gross": 0
          },
          {
            "cinema": "Krefeld",
            "session": "24641",
            "time": "2026-03-28T19:50:00",
            "sold": 20,
            "seats": 55,
            "gross": 312.80000000000007
          },
          {
            "cinema": "Regensburg",
            "session": "16138",
            "time": "2026-03-28T21:20:00",
            "sold": 33,
            "seats": 171,
            "gross": 494.6700000000002
          },
          {
            "cinema": "Berlin",
            "session": "54918",
            "time": "2026-03-28T12:00:00",
            "sold": 23,
            "seats": 102,
            "gross": 359.7700000000001
          },
          {
            "cinema": "Stuttgart Liederhalle",
            "session": "18144",
            "time": "2026-03-28T20:30:00",
            "sold": 136,
            "seats": 160,
            "gross": 2002.640000000001
          },
          {
            "cinema": "Berlin",
            "session": "54919",
            "time": "2026-03-28T19:45:00",
            "sold": 24,
            "seats": 102,
            "gross": 371.7600000000001
          },
          {
            "cinema": "Wuppertal",
            "session": "21225",
            "time": "2026-03-28T20:40:00",
            "sold": 9,
            "seats": 140,
            "gross": 134.91
          },
          {
            "cinema": "Wolfsburg",
            "session": "14977",
            "time": "2026-03-28T21:00:00",
            "sold": 6,
            "seats": 163,
            "gross": 89.94
          },
          {
            "cinema": "Freiburg",
            "session": "19359",
            "time": "2026-03-28T11:45:00",
            "sold": 5,
            "seats": 60,
            "gross": 80.94999999999999
          },
          {
            "cinema": "M\u00fcnchen",
            "session": "15926",
            "time": "2026-03-28T19:30:00",
            "sold": 5,
            "seats": 92,
            "gross": 83.94999999999999
          },
          {
            "cinema": "Kiel",
            "session": "48250",
            "time": "2026-03-28T20:30:00",
            "sold": 0,
            "seats": 94,
            "gross": 0
          },
          {
            "cinema": "Offenbach",
            "session": "17030",
            "time": "2026-03-28T20:30:00",
            "sold": 0,
            "seats": 171,
            "gross": 0
          },
          {
            "cinema": "Bremen",
            "session": "21454",
            "time": "2026-03-28T20:00:00",
            "sold": 2,
            "seats": 178,
            "gross": 29.98
          },
          {
            "cinema": "Augsburg",
            "session": "26242",
            "time": "2026-03-28T19:50:00",
            "sold": 2,
            "seats": 154,
            "gross": 27.98
          },
          {
            "cinema": "W\u00fcrzburg",
            "session": "15581",
            "time": "2026-03-28T19:30:00",
            "sold": 6,
            "seats": 131,
            "gross": 90.94
          },
          {
            "cinema": "G\u00f6ttingen",
            "session": "21608",
            "time": "2026-03-28T20:30:00",
            "sold": 0,
            "seats": 135,
            "gross": 0
          },
          {
            "cinema": "Sindelfingen",
            "session": "18737",
            "time": "2026-03-28T21:40:00",
            "sold": 6,
            "seats": 64,
            "gross": 99.93999999999998
          },
          {
            "cinema": "Dresden",
            "session": "18079",
            "time": "2026-03-28T19:00:00",
            "sold": 0,
            "seats": 194,
            "gross": 0
          },
          {
            "cinema": "Hannover",
            "session": "26353",
            "time": "2026-03-28T19:15:00",
            "sold": 3,
            "seats": 227,
            "gross": 35.97
          },
          {
            "cinema": "Halle",
            "session": "18567",
            "time": "2026-03-28T20:40:00",
            "sold": 2,
            "seats": 136,
            "gross": 29.98
          },
          {
            "cinema": "Berlin",
            "session": "54049",
            "time": "2026-03-28T20:20:00",
            "sold": 110,
            "seats": 114,
            "gross": 1513.9000000000008
          },
          {
            "cinema": "Trier",
            "session": "14243",
            "time": "2026-03-28T20:00:00",
            "sold": 1,
            "seats": 244,
            "gross": 14.99
          },
          {
            "cinema": "Magdeburg",
            "session": "34285",
            "time": "2026-03-28T19:30:00",
            "sold": 7,
            "seats": 81,
            "gross": 110.92999999999999
          },
          {
            "cinema": "Essen",
            "session": "41261",
            "time": "2026-03-28T20:15:00",
            "sold": 4,
            "seats": 291,
            "gross": 61.96
          }
        ]
      }
    }
  },
  "HO00001339": {
    "name": "Ustaad Bhagat Singh",
    "dates": {
      "2026-03-24": {
        "summary": {
          "shows": 0,
          "sold": 0,
          "seats": 0,
          "occupancy": 0,
          "gross": 0
        },
        "shows": []
      },
      "2026-03-26": {
        "summary": {
          "shows": 0,
          "sold": 0,
          "seats": 0,
          "occupancy": 0,
          "gross": 0
        },
        "shows": []
      },
      "2026-03-25": {
        "summary": {
          "shows": 0,
          "sold": 0,
          "seats": 0,
          "occupancy": 0,
          "gross": 0
        },
        "shows": []
      },
      "2026-03-27": {
        "summary": {
          "shows": 0,
          "sold": 0,
          "seats": 0,
          "occupancy": 0,
          "gross": 0
        },
        "shows": []
      },
      "2026-03-28": {
        "summary": {
          "shows": 0,
          "sold": 0,
          "seats": 0,
          "occupancy": 0,
          "gross": 0
        },
        "shows": []
      },
      "2026-03-29": {
        "summary": {
          "shows": 0,
          "sold": 0,
          "seats": 0,
          "occupancy": 0,
          "gross": 0
        },
        "shows": []
      },
      "2026-03-30": {
        "summary": {
          "shows": 0,
          "sold": 0,
          "seats": 0,
          "occupancy": 0,
          "gross": 0
        },
        "shows": []
      }
    }
  }
}